CHANGES.txt
COPYRIGHT.txt
LICENSE.txt
README.txt
bootstrap.py
buildout.cfg
setup.py
src/zc/__init__.py
src/zc.freeze.egg-info/PKG-INFO
src/zc.freeze.egg-info/SOURCES.txt
src/zc.freeze.egg-info/dependency_links.txt
src/zc.freeze.egg-info/namespace_packages.txt
src/zc.freeze.egg-info/not-zip-safe
src/zc.freeze.egg-info/requires.txt
src/zc.freeze.egg-info/top_level.txt
src/zc/freeze/README.txt
src/zc/freeze/__init__.py
src/zc/freeze/configure.zcml
src/zc/freeze/copier.py
src/zc/freeze/copier.txt
src/zc/freeze/interfaces.py
src/zc/freeze/subscribers.py
src/zc/freeze/subscribers.txt
src/zc/freeze/testing.py
src/zc/freeze/tests.py